combined_gene_caller/__init__.py
combined_gene_caller/__main__.py
combined_gene_caller/cli.py
combined_gene_caller-1.0.4.dist-info/AUTHORS.md
combined_gene_caller-1.0.4.dist-info/LICENSE
combined_gene_caller-1.0.4.dist-info/METADATA
combined_gene_caller-1.0.4.dist-info/WHEEL
combined_gene_caller-1.0.4.dist-info/entry_points.txt
combined_gene_caller-1.0.4.dist-info/top_level.txt
combined_gene_caller-1.0.4.dist-info/RECORD
