Metadata-Version: 2.1
Name: combined-gene-caller
Version: 1.0.4
Summary: Combined gene caller for MGnify pipeline, to combine predictions from FragGeneScan and Prodigal
Author-email: MGnify team <metagenomics-help@ebi.ac.uk>
License: Apache Software License 2.0
Keywords: bioinformatics,gene,metagenomics
Classifier: Programming Language :: Python :: 3
Classifier: License :: OSI Approved :: Apache Software License
Classifier: Operating System :: OS Independent
Requires-Python: >=3.9
License-File: LICENSE
License-File: AUTHORS.md
Requires-Dist: biopython ==1.81
Provides-Extra: dev
Requires-Dist: pre-commit ==3.3.3 ; extra == 'dev'
Requires-Dist: black ==23.7.0 ; extra == 'dev'
Requires-Dist: isort ==5.12.0 ; extra == 'dev'
Requires-Dist: bump-my-version ==0.9.2 ; extra == 'dev'
Provides-Extra: test
Requires-Dist: pytest-workflow ==2.0.1 ; extra == 'test'
